{
	"author": "Dustin Morgan <morgan@aspendenver.org>",
	"dependencies": [{
			"name": "puppetlabs/mysql",
			"version_requirement": ">= 3.6.0"
		},{
			"name": "swizzley88/artifact",
			"version_requirement": ">= 0.1.3"
		},{
			"name": "puppetlabs/apache",
			"version_requirement": ">= 1.6.0"
		}
	],
	"license": "Apache-2.0",
	"name": "swizzley88-lamp",
	"operatingsystem_support": [{
			"operatingsystem": "RedHat",
			"operatingsystemrelease": [ "6"
			]
		}
	],
	"project_page": "https://github.com/swizzley/puppet-lamp",
	"issues_url": "https://github.com/swizzley/puppet-lamp/issues",
	"requirements": [{
			"name": "pe",
			"version_requirement": ">= 3.7.0 < 2015.3.0"
		},{
			"name": "puppet",
			"version_requirement": ">= 3.0.0 < 5.0.0"
		}
	],
	"source": "https://github.com/swizzley/puppet-lamp",
	"summary": "lamp module for EL 6",
	"tags": [ "lamp",
		"php",
		"website",
		"LAMP"
	],
	"version": "0.1.2"
}
